opthedgehog/AcousticsCells.py
opthedgehog/AcoustoopticCells.py
opthedgehog/AlignmentMarkers.py
opthedgehog/IDTcells.py
opthedgehog/PositiveMaskCells.py
opthedgehog/__init__.py
opthedgehog/config.py
opthedgehog/electronicFootprint.py
opthedgehog/inOutCoupler.py
opthedgehog/legacy.py
opthedgehog/optCells.py
opthedgehog/suspendedOptCell.py
opthedgehog/utility.py
opthedgehog-0.3.11.dist-info/LICENSE
opthedgehog-0.3.11.dist-info/METADATA
opthedgehog-0.3.11.dist-info/WHEEL
opthedgehog-0.3.11.dist-info/top_level.txt
opthedgehog-0.3.11.dist-info/RECORD
