Metadata-Version: 2.1
Name: opthedgehog
Version: 0.3.11
Summary: A python module to generate mask for integrated optics and acoustics
Home-page: UNKNOWN
Author: Linbo Shao
Author-email: mail@linbo-shao.com
License: UNKNOWN
Platform: UNKNOWN
Classifier: Development Status :: 3 - Alpha
Classifier: Programming Language :: Python :: 3.8
Classifier: Operating System :: OS Independent
Requires-Dist: numpy (>1.12.0)
Requires-Dist: bezier (>2020)
Requires-Dist: gdspy (>1.5.2)
Requires-Dist: termcolor
